airpilot/__init__.py
airpilot/builders/__init__.py
airpilot/builders/config.py
airpilot/builders/content.py
airpilot/builders/domains.py
airpilot/builders/scaffold.py
airpilot/cli.py
airpilot/commands/__init__.py
airpilot/commands/init.py
airpilot/commands/license.py
airpilot/commands/pull.py
airpilot/commands/push.py
airpilot/commands/status.py
airpilot/commands/sync.py
airpilot/license.py
airpilot/py.typed
airpilot/ui/__init__.py
airpilot/ui/panels.py
airpilot/ui/prompts.py
airpilot/utils/__init__.py
airpilot/utils/backup.py
airpilot/utils/git.py
airpilot/utils/version.py
airpilot-0.9.0.dist-info/WHEEL
airpilot-0.9.0.dist-info/entry_points.txt
airpilot-0.9.0.dist-info/METADATA
airpilot-0.9.0.dist-info/RECORD
