Metadata-Version: 2.3
Name: airpilot
Version: 0.9.0
Summary: Universal Intelligence Control
Keywords: ai,assistant,rules,management,vscode,cli,configuration
Author: Shane Holloman
Author-email: Shane Holloman <shaneholloman@gmail.com>
License: Elastic-2.0
Classifier: Development Status :: 1 - Planning
Classifier: Intended Audience :: Developers
Classifier: License :: Other/Proprietary License
Classifier: Operating System :: OS Independent
Classifier: Programming Language :: Python :: 3
Classifier: Programming Language :: Python :: 3.8
Classifier: Programming Language :: Python :: 3.9
Classifier: Programming Language :: Python :: 3.10
Classifier: Programming Language :: Python :: 3.11
Classifier: Programming Language :: Python :: 3.12
Requires-Dist: click>=8.0.0
Requires-Dist: rich>=13.0.0
Requires-Dist: ty ; extra == 'dev'
Requires-Dist: ruff ; extra == 'dev'
Requires-Dist: pytest>=7.0.0 ; extra == 'dev'
Maintainer: Shane Holloman
Maintainer-email: Shane Holloman <shaneholloman@gmail.com>
Requires-Python: >=3.8
Project-URL: Homepage, https://github.com/shaneholloman/airpilot
Project-URL: Issues, https://github.com/shaneholloman/airpilot/issues
Project-URL: Repository, https://github.com/shaneholloman/airpilot.git
Provides-Extra: dev
